py8chan/__init__.py
py8chan/board.py
py8chan/file.py
py8chan/post.py
py8chan/thread.py
py8chan/url.py
py8chan/util.py
py8chan-0.2.2.dist-info/LICENSE
py8chan-0.2.2.dist-info/METADATA
py8chan-0.2.2.dist-info/WHEEL
py8chan-0.2.2.dist-info/top_level.txt
py8chan-0.2.2.dist-info/RECORD
