Metadata-Version: 2.1
Name: py8chan
Version: 0.2.2
Summary: Python 8chan/vichan API Wrapper. Based on BASC-py4chan by the Bbiliotheca Anonoma
Home-page: http://github.com/bibanon/py8chan
Author: Antonizoon
Author-email: antonizoon@bibanon.org
License: DO WHAT THE FUCK YOU WANT TO PUBLIC LICENSE
Keywords: 8chan api vichan
Classifier: Intended Audience :: Developers
Classifier: Natural Language :: English
Classifier: Programming Language :: Python :: 2
Classifier: Programming Language :: Python :: 3
License-File: LICENSE
Requires-Dist: requests (>=1.0.0)
